rotate_backups/__init__.py
rotate_backups/cli.py
rotate_backups/tests.py
rotate_backups-8.1.dist-info/LICENSE.txt
rotate_backups-8.1.dist-info/METADATA
rotate_backups-8.1.dist-info/WHEEL
rotate_backups-8.1.dist-info/entry_points.txt
rotate_backups-8.1.dist-info/top_level.txt
rotate_backups-8.1.dist-info/RECORD
