Metadata-Version: 2.1
Name: rotate-backups
Version: 8.1
Summary: Simple command line interface for backup rotation
Home-page: https://github.com/xolox/python-rotate-backups
Author: Peter Odding
Author-email: peter@peterodding.com
License: MIT
Platform: UNKNOWN
Classifier: Development Status :: 5 - Production/Stable
Classifier: Environment :: Console
Classifier: Intended Audience :: Developers
Classifier: Intended Audience :: System Administrators
Classifier: License :: OSI Approved :: MIT License
Classifier: Operating System :: MacOS :: MacOS X
Classifier: Operating System :: POSIX
Classifier: Operating System :: POSIX :: Linux
Classifier: Operating System :: Unix
Classifier: Programming Language :: Python
Classifier: Programming Language :: Python :: 2
Classifier: Programming Language :: Python :: 2.7
Classifier: Programming Language :: Python :: 3
Classifier: Programming Language :: Python :: 3.5
Classifier: Programming Language :: Python :: 3.6
Classifier: Programming Language :: Python :: 3.7
Classifier: Programming Language :: Python :: 3.8
Classifier: Programming Language :: Python :: Implementation :: CPython
Classifier: Programming Language :: Python :: Implementation :: PyPy
Classifier: Topic :: Software Development :: Libraries :: Python Modules
Classifier: Topic :: Software Development
Classifier: Topic :: System :: Archiving :: Backup
Classifier: Topic :: System :: Systems Administration
Requires-Python: >=2.7, !=3.0.*, !=3.1.*, !=3.2.*, !=3.3.*, !=3.4.*
Requires-Dist: coloredlogs (>=5.1)
Requires-Dist: executor (>=23.1)
Requires-Dist: humanfriendly (>=8.0)
Requires-Dist: naturalsort (>=1.4)
Requires-Dist: property-manager (>=3.0)
Requires-Dist: python-dateutil (>=2.2)
Requires-Dist: simpleeval (>=0.8.7)
Requires-Dist: six (>=1.9.0)
Requires-Dist: update-dotdee (>=6.0)
Requires-Dist: verboselogs (>=1.5)
